HoloEcho/HoloEcho.py
HoloEcho/__init__.py
holoecho-0.2.2.dist-info/METADATA
holoecho-0.2.2.dist-info/WHEEL
holoecho-0.2.2.dist-info/top_level.txt
holoecho-0.2.2.dist-info/RECORD
