Metadata-Version: 2.4
Name: HoloEcho
Version: 0.2.2
Summary: Modern STT AND TTS for modern AI-projects
Author: Tristan McBride Sr.
Author-email: "Tristan McBride Sr." <142635792+TristanMcBrideSr@users.noreply.github.com>
Maintainer-email: "Tristan McBride Sr." <142635792+TristanMcBrideSr@users.noreply.github.com>
License-Expression: Apache-2.0
Project-URL: Homepage, https://github.com/TristanMcBrideSr
Keywords: AI,Agents,Speech Recognition,Text to Speech,Productivity,Automation
Classifier: Programming Language :: Python :: 3
Classifier: Operating System :: OS Independent
Classifier: Intended Audience :: Developers
Requires-Python: >=3.10
Requires-Dist: python-dotenv
Requires-Dist: HoloWave
Requires-Dist: HoloTTS
Requires-Dist: HoloSTT
Dynamic: author
